astload/__init__.py
astload-0.1.1.dist-info/LICENSE
astload-0.1.1.dist-info/METADATA
astload-0.1.1.dist-info/WHEEL
astload-0.1.1.dist-info/top_level.txt
astload-0.1.1.dist-info/RECORD
